cfloader/__init__.py
cfloader/fs.py
cfloader/loader.py
cfloader/readers.py
cfloader-0.1.4.dist-info/AUTHORS.rst
cfloader-0.1.4.dist-info/LICENSE
cfloader-0.1.4.dist-info/METADATA
cfloader-0.1.4.dist-info/WHEEL
cfloader-0.1.4.dist-info/top_level.txt
cfloader-0.1.4.dist-info/RECORD
