Metadata-Version: 1.2
Name: cfloader
Version: 0.1.4
Summary: Loads python modules from a configuration file.
Home-page: https://github.com/shachibista/cfloader
Author: Shachi Bista
Author-email: shachibista@gmail.com
License: MIT license
Keywords: cfloader
Platform: UNKNOWN
Classifier: Development Status :: 2 - Pre-Alpha
Classifier: Intended Audience :: Developers
Classifier: License :: OSI Approved :: MIT License
Classifier: Natural Language :: English
Classifier: Programming Language :: Python :: 3
Classifier: Programming Language :: Python :: 3.7
Classifier: Programming Language :: Python :: 3.8
Requires-Python: >=3.7
